README.md
setup.py
mlopt/__init__.py
mlopt/error.py
mlopt/filter.py
mlopt/kkt.py
mlopt/optimizer.py
mlopt/problem.py
mlopt/sampling.py
mlopt/settings.py
mlopt/strategy.py
mlopt/utils.py
mlopt.egg-info/PKG-INFO
mlopt.egg-info/SOURCES.txt
mlopt.egg-info/dependency_links.txt
mlopt.egg-info/requires.txt
mlopt.egg-info/top_level.txt
mlopt/learners/__init__.py
mlopt/learners/learner.py
mlopt/tests/__init__.py
mlopt/tests/settings.py
mlopt/tests/test_caching.py
mlopt/tests/test_filter.py
mlopt/tests/test_kkt_solver.py
mlopt/tests/test_matrix_parameters.py
mlopt/tests/test_parallel.py
mlopt/tests/test_parameters.py
mlopt/tests/test_problem.py
mlopt/tests/test_sampling.py
mlopt/tests/test_save.py
mlopt/tests/test_solve_strategy.py