Metadata-Version: 2.1
Name: mlopt
Version: 0.0.2
Summary: The Machine Learning Optimizer
Home-page: https://mlopt.org/
Author: Bartolomeo Stellato, Dimitris Bertsimas
Author-email: bartolomeo.stellato@gmail.com
License: Apache License, Version 2.0
Platform: UNKNOWN
